{
  "ETH": {
    "chainId": 1,
    "address": "0x0000000000000000000000000000000000000000",
    "decimals": 18,
    "symbol": "ETH",
    "name": "Ethereum"
  },
  "WETH": {
    "chainId": 1,
    "address": "0xC02aaA39b223FE8D0A0e5C4F27eAD9083C756Cc2",
    "decimals": 18,
    "symbol": "WETH",
    "name": "Wrapped Ether"
  },
  "aEthWETH": {
    "chainId": 1,
    "address": "0x4d5F47FA6A74757f35C14fD3a6Ef8E3C9BC514E8",
    "decimals": 18,
    "symbol": "aEthWETH",
    "name": "Aave Ethereum WETH"
  },
  "wstETH": {
    "chainId": 1,
    "address": "0x7f39C581F595B53c5cb19bD0b3f8dA6c935E2Ca0",
    "decimals": 18,
    "symbol": "wstETH",
    "name": "Wrapped liquid staked Ether 2.0"
  },
  "aEthwstETH": {
    "chainId": 1,
    "address": "0x0B925eD163218f6662a35e0f0371Ac234f9E9371",
    "decimals": 18,
    "symbol": "aEthwstETH",
    "name": "Aave Ethereum wstETH"
  },
  "WBTC": {
    "chainId": 1,
    "address": "0x2260FAC5E5542a773Aa44fBCfeDf7C193bc2C599",
    "decimals": 8,
    "symbol": "WBTC",
    "name": "Wrapped BTC"
  },
  "aEthWBTC": {
    "chainId": 1,
    "address": "0x5Ee5bf7ae06D1Be5997A1A72006FE6C607eC6DE8",
    "decimals": 8,
    "symbol": "aEthWBTC",
    "name": "Aave Ethereum WBTC"
  },
  "USDC": {
    "chainId": 1,
    "address": "0xA0b86991c6218b36c1d19D4a2e9Eb0cE3606eB48",
    "decimals": 6,
    "symbol": "USDC",
    "name": "USD Coin"
  },
  "aEthUSDC": {
    "chainId": 1,
    "address": "0x98C23E9d8f34FEFb1B7BD6a91B7FF122F4e16F5c",
    "decimals": 6,
    "symbol": "aEthUSDC",
    "name": "Aave Ethereum USDC"
  },
  "DAI": {
    "chainId": 1,
    "address": "0x6B175474E89094C44Da98b954EedeAC495271d0F",
    "decimals": 18,
    "symbol": "DAI",
    "name": "Dai Stablecoin"
  },
  "aEthDAI": {
    "chainId": 1,
    "address": "0x018008bfb33d285247A21d44E50697654f754e63",
    "decimals": 18,
    "symbol": "aEthDAI",
    "name": "Aave Ethereum DAI"
  },
  "LINK": {
    "chainId": 1,
    "address": "0x514910771AF9Ca656af840dff83E8264EcF986CA",
    "decimals": 18,
    "symbol": "LINK",
    "name": "ChainLink Token"
  },
  "aEthLINK": {
    "chainId": 1,
    "address": "0x5E8C8A7243651DB1384C0dDfDbE39761E8e7E51a",
    "decimals": 18,
    "symbol": "aEthLINK",
    "name": "Aave Ethereum LINK"
  },
  "AAVE": {
    "chainId": 1,
    "address": "0x7Fc66500c84A76Ad7e9c93437bFc5Ac33E2DDaE9",
    "decimals": 18,
    "symbol": "AAVE",
    "name": "Aave Token"
  },
  "aEthAAVE": {
    "chainId": 1,
    "address": "0xA700b4eB416Be35b2911fd5Dee80678ff64fF6C9",
    "decimals": 18,
    "symbol": "aEthAAVE",
    "name": "Aave Ethereum AAVE"
  },
  "cbETH": {
    "chainId": 1,
    "address": "0xBe9895146f7AF43049ca1c1AE358B0541Ea49704",
    "decimals": 18,
    "symbol": "cbETH",
    "name": "Coinbase Wrapped Staked ETH"
  },
  "aEthcbETH": {
    "chainId": 1,
    "address": "0x977b6fc5dE62598B08C85AC8Cf2b745874E8b78c",
    "decimals": 18,
    "symbol": "aEthcbETH",
    "name": "Aave Ethereum cbETH"
  },
  "USDT": {
    "chainId": 1,
    "address": "0xdAC17F958D2ee523a2206206994597C13D831ec7",
    "decimals": 6,
    "symbol": "USDT",
    "name": "Tether USD"
  },
  "aEthUSDT": {
    "chainId": 1,
    "address": "0x23878914EFE38d27C4D67Ab83ed1b93A74D4086a",
    "decimals": 6,
    "symbol": "aEthUSDT",
    "name": "Aave Ethereum USDT"
  },
  "rETH": {
    "chainId": 1,
    "address": "0xae78736Cd615f374D3085123A210448E74Fc6393",
    "decimals": 18,
    "symbol": "rETH",
    "name": "Rocket Pool ETH"
  },
  "aEthrETH": {
    "chainId": 1,
    "address": "0xCc9EE9483f662091a1de4795249E24aC0aC2630f",
    "decimals": 18,
    "symbol": "aEthrETH",
    "name": "Aave Ethereum rETH"
  },
  "LUSD": {
    "chainId": 1,
    "address": "0x5f98805A4E8be255a32880FDeC7F6728C6568bA0",
    "decimals": 18,
    "symbol": "LUSD",
    "name": "LUSD Stablecoin"
  },
  "aEthLUSD": {
    "chainId": 1,
    "address": "0x3Fe6a295459FAe07DF8A0ceCC36F37160FE86AA9",
    "decimals": 18,
    "symbol": "aEthLUSD",
    "name": "Aave Ethereum LUSD"
  },
  "CRV": {
    "chainId": 1,
    "address": "0xD533a949740bb3306d119CC777fa900bA034cd52",
    "decimals": 18,
    "symbol": "CRV",
    "name": "Curve DAO Token"
  },
  "aEthCRV": {
    "chainId": 1,
    "address": "0x7B95Ec873268a6BFC6427e7a28e396Db9D0ebc65",
    "decimals": 18,
    "symbol": "aEthCRV",
    "name": "Aave Ethereum CRV"
  },
  "MKR": {
    "chainId": 1,
    "address": "0x9f8F72aA9304c8B593d555F12eF6589cC3A579A2",
    "decimals": 18,
    "symbol": "MKR",
    "name": "Maker"
  },
  "aEthMKR": {
    "chainId": 1,
    "address": "0x8A458A9dc9048e005d22849F470891b840296619",
    "decimals": 18,
    "symbol": "aEthMKR",
    "name": "Aave Ethereum MKR"
  },
  "SNX": {
    "chainId": 1,
    "address": "0xC011a73ee8576Fb46F5E1c5751cA3B9Fe0af2a6F",
    "decimals": 18,
    "symbol": "SNX",
    "name": "Synthetix Network Token"
  },
  "aEthSNX": {
    "chainId": 1,
    "address": "0xC7B4c17861357B8ABB91F25581E7263E08DCB59c",
    "decimals": 18,
    "symbol": "aEthSNX",
    "name": "Aave Ethereum SNX"
  },
  "BAL": {
    "chainId": 1,
    "address": "0xba100000625a3754423978a60c9317c58a424e3D",
    "decimals": 18,
    "symbol": "BAL",
    "name": "Balancer"
  },
  "aEthBAL": {
    "chainId": 1,
    "address": "0x2516E7B3F76294e03C42AA4c5b5b4DCE9C436fB8",
    "decimals": 18,
    "symbol": "aEthBAL",
    "name": "Aave Ethereum BAL"
  },
  "UNI": {
    "chainId": 1,
    "address": "0x1f9840a85d5aF5bf1D1762F925BDADdC4201F984",
    "decimals": 18,
    "symbol": "UNI",
    "name": "Uniswap"
  },
  "aEthUNI": {
    "chainId": 1,
    "address": "0xF6D2224916DDFbbab6e6bd0D1B7034f4Ae0CaB18",
    "decimals": 18,
    "symbol": "aEthUNI",
    "name": "Aave Ethereum UNI"
  },
  "LDO": {
    "chainId": 1,
    "address": "0x5A98FcBEA516Cf06857215779Fd812CA3beF1B32",
    "decimals": 18,
    "symbol": "LDO",
    "name": "Lido DAO Token"
  },
  "aEthLDO": {
    "chainId": 1,
    "address": "0x9A44fd41566876A39655f74971a3A6eA0a17a454",
    "decimals": 18,
    "symbol": "aEthLDO",
    "name": "Aave Ethereum LDO"
  },
  "ENS": {
    "chainId": 1,
    "address": "0xC18360217D8F7Ab5e7c516566761Ea12Ce7F9D72",
    "decimals": 18,
    "symbol": "ENS",
    "name": "Ethereum Name Service"
  },
  "aEthENS": {
    "chainId": 1,
    "address": "0x545bD6c032eFdde65A377A6719DEF2796C8E0f2e",
    "decimals": 18,
    "symbol": "aEthENS",
    "name": "Aave Ethereum ENS"
  },
  "1INCH": {
    "chainId": 1,
    "address": "0x111111111117dC0aa78b770fA6A738034120C302",
    "decimals": 18,
    "symbol": "1INCH",
    "name": "1INCH Token"
  },
  "aEth1INCH": {
    "chainId": 1,
    "address": "0x71Aef7b30728b9BB371578f36c5A1f1502a5723e",
    "decimals": 18,
    "symbol": "aEth1INCH",
    "name": "Aave Ethereum 1INCH"
  },
  "FRAX": {
    "chainId": 1,
    "address": "0x853d955aCEf822Db058eb8505911ED77F175b99e",
    "decimals": 18,
    "symbol": "FRAX",
    "name": "Frax"
  },
  "aEthFRAX": {
    "chainId": 1,
    "address": "0xd4e245848d6E1220DBE62e155d89fa327E43CB06",
    "decimals": 18,
    "symbol": "aEthFRAX",
    "name": "Aave Ethereum FRAX"
  },
  "GHO": {
    "chainId": 1,
    "address": "0x40D16FC0246aD3160Ccc09B8D0D3A2cD28aE6C2f",
    "decimals": 18,
    "symbol": "GHO",
    "name": "Gho Token"
  },
  "aEthGHO": {
    "chainId": 1,
    "address": "0x00907f9921424583e7ffBfEdf84F92B7B2Be4977",
    "decimals": 18,
    "symbol": "aEthGHO",
    "name": "Aave Ethereum GHO"
  },
  "RPL": {
    "chainId": 1,
    "address": "0xD33526068D116cE69F19A9ee46F0bd304F21A51f",
    "decimals": 18,
    "symbol": "RPL",
    "name": "Rocket Pool Protocol"
  },
  "aEthRPL": {
    "chainId": 1,
    "address": "0xB76CF92076adBF1D9C39294FA8e7A67579FDe357",
    "decimals": 18,
    "symbol": "aEthRPL",
    "name": "Aave Ethereum RPL"
  },
  "sDAI": {
    "chainId": 1,
    "address": "0x83F20F44975D03b1b09e64809B757c47f942BEeA",
    "decimals": 18,
    "symbol": "sDAI",
    "name": "Savings Dai"
  },
  "aEthsDAI": {
    "chainId": 1,
    "address": "0x4C612E3B15b96Ff9A6faED838F8d07d479a8dD4c",
    "decimals": 18,
    "symbol": "aEthsDAI",
    "name": "Aave Ethereum sDAI"
  },
  "STG": {
    "chainId": 1,
    "address": "0xAf5191B0De278C7286d6C7CC6ab6BB8A73bA2Cd6",
    "decimals": 18,
    "symbol": "STG",
    "name": "StargateToken"
  },
  "aEthSTG": {
    "chainId": 1,
    "address": "0x1bA9843bD4327c6c77011406dE5fA8749F7E3479",
    "decimals": 18,
    "symbol": "aEthSTG",
    "name": "Aave Ethereum STG"
  },
  "KNC": {
    "chainId": 1,
    "address": "0xdeFA4e8a7bcBA345F687a2f1456F5Edd9CE97202",
    "decimals": 18,
    "symbol": "KNC",
    "name": "Kyber Network Crystal v2"
  },
  "aEthKNC": {
    "chainId": 1,
    "address": "0x5b502e3796385E1e9755d7043B9C945C3aCCeC9C",
    "decimals": 18,
    "symbol": "aEthKNC",
    "name": "Aave Ethereum KNC"
  },
  "FXS": {
    "chainId": 1,
    "address": "0x3432B6A60D23Ca0dFCa7761B7ab56459D9C964D0",
    "decimals": 18,
    "symbol": "FXS",
    "name": "Frax Share"
  },
  "aEthFXS": {
    "chainId": 1,
    "address": "0x82F9c5ad306BBa1AD0De49bB5FA6F01bf61085ef",
    "decimals": 18,
    "symbol": "aEthFXS",
    "name": "Aave Ethereum FXS"
  }
}
